{
  "image_properties": {
    "dimensions": [
      2074,
      1178
    ],
    "format": "PNG",
    "mode": "RGBA",
    "aspect_ratio": 1.7606112054329373
  },
  "dominant_colors": [
    {
      "rgb": [
        5.060069671956674,
        5.996279430396687,
        15.954165028588498
      ],
      "hex": "#05050f",
      "percentage": 37.48078317858914
    },
    {
      "rgb": [
        6.923136104107623,
        12.81428837295555,
        28.71921921423469
      ],
      "hex": "#060c1c",
      "percentage": 24.632076660996443
    },
    {
      "rgb": [
        9.014608372678916,
        20.66105175051908,
        42.32034774989205
      ],
      "hex": "#09142a",
      "percentage": 12.517006579970626
    },
    {
      "rgb": [
        25.038703838317787,
        27.10628055472146,
        48.02736206724063
      ],
      "hex": "#191b30",
      "percentage": 11.484496384208725
    },
    {
      "rgb": [
        15.112531819399992,
        35.20806538049072,
        65.729593716508
      ],
      "hex": "#0f2341",
      "percentage": 4.884388000517361
    },
    {
      "rgb": [
        25.906086539682875,
        57.36712394433426,
        88.41056297319483
      ],
      "hex": "#193958",
      "percentage": 2.9067130762795252
    },
    {
      "rgb": [
        44.518277007961004,
        48.75122787217354,
        61.37680523334822
      ],
      "hex": "#2c303d",
      "percentage": 1.9584785680255012
    },
    {
      "rgb": [
        42.43439565473537,
        85.95811792421694,
        117.62021464564151
      ],
      "hex": "#2a5575",
      "percentage": 1.2549259732839113
    },
    {
      "rgb": [
        250.90745617336057,
        250.93589647129323,
        251.24832593483228
      ],
      "hex": "#fafafb",
      "percentage": 1.0880118141498019
    },
    {
      "rgb": [
        72.46618670118238,
        136.9101278110312,
        162.51326646173908
      ],
      "hex": "#4888a2",
      "percentage": 0.5067592457673876
    },
    {
      "rgb": [
        102.41486359360358,
        112.71044214487117,
        101.74506114769522
      ],
      "hex": "#667065",
      "percentage": 0.4343533734014633
    },
    {
      "rgb": [
        105.35582822086093,
        59.656727065201146,
        233.10814666857112
      ],
      "hex": "#693be9",
      "percentage": 0.2868811528619352
    },
    {
      "rgb": [
        171.2504743833023,
        172.71568627450785,
        180.76976597090538
      ],
      "hex": "#abacb4",
      "percentage": 0.2588438308886971
    },
    {
      "rgb": [
        109.35564096767052,
        229.1214108071417,
        226.56070540357376
      ],
      "hex": "#6de5e2",
      "percentage": 0.18103514611333135
    },
    {
      "rgb": [
        236.7361201828841,
        133.73938602220525,
        102.86675375571647
      ],
      "hex": "#ec8566",
      "percentage": 0.1252470149461438
    }
  ],
  "blue_contour_variations": [
    {
      "rgb": [
        38.99356553363867,
        80.1120436424668,
        116.93579521611404
      ],
      "hex": "#265074"
    },
    {
      "rgb": [
        208.41992475053004,
        212.38180925895608,
        219.35187305741783
      ],
      "hex": "#d0d4db"
    },
    {
      "rgb": [
        120.18888121546979,
        122.57021178637177,
        143.74827348066304
      ],
      "hex": "#787a8f"
    },
    {
      "rgb": [
        67.04769721842257,
        142.59443684450486,
        166.87387140902848
      ],
      "hex": "#438ea6"
    },
    {
      "rgb": [
        105.43495644723704,
        59.66857061259392,
        233.15893188633527
      ],
      "hex": "#693be9"
    }
  ],
  "background_color": {
    "rgb": [
      5.060069671956674,
      5.996279430396687,
      15.954165028588498
    ],
    "hex": "#05050f",
    "percentage": 37.48078317858914
  },
  "typescript_constants": {
    "BACKGROUND_COLOR": "#05050f",
    "DOMINANT_COLORS": [
      "#05050f",
      "#060c1c",
      "#09142a",
      "#191b30",
      "#0f2341"
    ],
    "BLUE_CONTOUR_VARIATIONS": [
      "#265074",
      "#d0d4db",
      "#787a8f",
      "#438ea6",
      "#693be9"
    ],
    "COLOR_PALETTE": {
      "background": "#05050f",
      "primary_blue": "#265074",
      "secondary_blue": "#d0d4db",
      "accent_blue": "#787a8f"
    },
    "OPACITY_LEVELS": {
      "primary_contours": 0.8,
      "secondary_contours": 0.6,
      "background_contours": 0.4,
      "accent_glow": 0.3
    },
    "STROKE_WEIGHTS": {
      "major_contours": 2,
      "medium_contours": 1.5,
      "minor_contours": 1,
      "detail_lines": 0.8
    }
  },
  "analysis_summary": {
    "total_colors_found": 15,
    "blue_variations_found": 5,
    "background_identified": true,
    "image_dimensions": [
      2074,
      1178
    ],
    "aspect_ratio": 1.7606112054329373
  }
}